<?xml version="1.0" encoding="UTF-8"?>
<different>
 <id>80</id>
 <name>いちご狩り！</name>
 <difficulty>3</difficulty>
 <point><!--図画にある違う部分の座標。 -->
  <x>189</x><!--point のx座標 -->
  <y>69</y><!--point のy座標-->
 </point>
 <point><!--図画にある違う部分の座標。 -->
  <x>344</x><!--point のx座標 -->
  <y>77</y><!--point のy座標-->
 </point>
 <point><!--図画にある違う部分の座標。 -->
  <x>222</x><!--point のx座標 -->
  <y>199</y><!--point のy座標-->
 </point>
 <point><!--図画にある違う部分の座標。 -->
  <x>322</x><!--point のx座標 -->
  <y>249</y><!--point のy座標-->
 </point>
 <point><!--図画にある違う部分の座標。 -->
  <x>368</x><!--point のx座標 -->
  <y>377</y><!--point のy座標-->
 </point>
 <point><!--図画にある違う部分の座標。 -->
  <x>229</x><!--point のx座標 -->
  <y>357</y><!--point のy座標-->
 </point>
 <point><!--図画にある違う部分の座標。 -->
  <x>77</x><!--point のx座標 -->
  <y>247</y><!--point のy座標-->
 </point>
 <point><!--図画にある違う部分の座標。 -->
  <x>37</x><!--point のx座標 -->
  <y>355</y><!--point のy座標-->
 </point>
</different>