<?xml version="1.0" encoding="UTF-8"?>
<different>
 <id>288</id>
 <name>大海原をめざして</name>
 <difficulty>3</difficulty>
 <point><!--図画にある違う部分の座標。 -->
  <x>31</x><!--point のx座標 -->
  <y>71</y><!--point のy座標-->
 </point>
 <point><!--図画にある違う部分の座標。 -->
  <x>187</x><!--point のx座標 -->
  <y>91</y><!--point のy座標-->
 </point>
 <point><!--図画にある違う部分の座標。 -->
  <x>389</x><!--point のx座標 -->
  <y>63</y><!--point のy座標-->
 </point>
 <point><!--図画にある違う部分の座標。 -->
  <x>88</x><!--point のx座標 -->
  <y>229</y><!--point のy座標-->
 </point>
 <point><!--図画にある違う部分の座標。 -->
  <x>388</x><!--point のx座標 -->
  <y>235</y><!--point のy座標-->
 </point>
 <point><!--図画にある違う部分の座標。 -->
  <x>28</x><!--point のx座標 -->
  <y>360</y><!--point のy座標-->
 </point>
 <point><!--図画にある違う部分の座標。 -->
  <x>181</x><!--point のx座標 -->
  <y>373</y><!--point のy座標-->
 </point>
 <point><!--図画にある違う部分の座標。 -->
  <x>309</x><!--point のx座標 -->
  <y>456</y><!--point のy座標-->
 </point>
</different>