<?xml version="1.0" encoding="UTF-8"?>
<different>
 <id>78</id>
 <name>空中サイクリング</name>
 <difficulty>2</difficulty>
 <point><!--図画にある違う部分の座標。 -->
  <x>114</x><!--point のx座標 -->
  <y>70</y><!--point のy座標-->
 </point>
 <point><!--図画にある違う部分の座標。 -->
  <x>336</x><!--point のx座標 -->
  <y>60</y><!--point のy座標-->
 </point>
 <point><!--図画にある違う部分の座標。 -->
  <x>72</x><!--point のx座標 -->
  <y>281</y><!--point のy座標-->
 </point>
 <point><!--図画にある違う部分の座標。 -->
  <x>348</x><!--point のx座標 -->
  <y>344</y><!--point のy座標-->
 </point>
 <point><!--図画にある違う部分の座標。 -->
  <x>29</x><!--point のx座標 -->
  <y>516</y><!--point のy座標-->
 </point>
 <point><!--図画にある違う部分の座標。 -->
  <x>82</x><!--point のx座標 -->
  <y>587</y><!--point のy座標-->
 </point>
 <point><!--図画にある違う部分の座標。 -->
  <x>301</x><!--point のx座標 -->
  <y>685</y><!--point のy座標-->
 </point>
</different>